CHANGELOG.txt
LICENSE.txt
MANIFEST.in
README.txt
setup.py
neurettes/__init__.py
neurettes/neura.py
neurettes/neuros.py
neurettes.egg-info/PKG-INFO
neurettes.egg-info/SOURCES.txt
neurettes.egg-info/dependency_links.txt
neurettes.egg-info/top_level.txt